{"mediators":[{"view":"views.page06Scene","mediator":"mediators.page06Mediator","custom":""}],"commands":[{"event":"page06.ext_but_TOC_code_486","command":"commands.page06.ext_but_TOC_code_486","custom":""},{"event":"page06.gotoTOC_button_but_TOC","command":"commands.page06.gotoTOC_button_but_TOC","custom":""},{"event":"page06.gotoTitle_button_but_title","command":"commands.page06.gotoTitle_button_but_title","custom":""},{"event":"page06.ext_but_NextBook_code_014","command":"commands.page06.ext_but_NextBook_code_014","custom":""},{"event":"page06.gotoNextBook_button_but_NextBook","command":"commands.page06.gotoNextBook_button_but_NextBook","custom":""},{"event":"page06.ext_but_PrevBook_code_273","command":"commands.page06.ext_but_PrevBook_code_273","custom":""},{"event":"page06.gotoPreviousBoo_button_but_PrevBook","command":"commands.page06.gotoPreviousBoo_button_but_PrevBook","custom":""}]}